CellTypeGenomics_netzyron/__init__.py
CellTypeGenomics_netzyron/celltypegenomics.py
CellTypeGenomics_netzyron/json/cell_types_to_ensembl.json
CellTypeGenomics_netzyron/json/protein_atlas_ensembl_ids.json
celltypegenomics_netzyron-0.0.1.dist-info/METADATA
celltypegenomics_netzyron-0.0.1.dist-info/WHEEL
celltypegenomics_netzyron-0.0.1.dist-info/licenses/LICENSE
celltypegenomics_netzyron-0.0.1.dist-info/RECORD
